{
    "table": "jsontemplates",
    "PK_ColumnName": ["type", "id"],
    "setPKValue": ["type"],
    "schema":
    {
        "id": { "formFieldName": "jsontemplates:templateId", "bpType": "i", "defaultValue": null, "encrypt": false },
        "type" : { "formFieldName" : "jsontemplates:templateType", "bpType" : "s", "defaultValue" : "eventchecklist", "encrypt" : false },
        "name" : { "formFieldName" : "jsontemplates:name", "bpType" : "s", "defaultValue" : "Novo checklist", "encrypt" : false },
        "templateJson" : { "formFieldName" : "jsontemplates:templateJson", "bpType" : "s", "defaultValue" : "{ \"preevent\":[], \"eventdate\":[], \"postevent\":[]}", "encrypt" : false }
    }
}